{"Title":{"0":"A Fistful of Dollars","1":"A Fistful of Dollars","2":"A Fistful of Dollars"},"Year":{"0":"1964","1":"1964","2":"1964"},"Rated":{"0":"R","1":"R","2":"R"},"Released":{"0":"18 Jan 1967","1":"18 Jan 1967","2":"18 Jan 1967"},"Runtime":{"0":"99 min","1":"99 min","2":"99 min"},"Genre":{"0":"Action, Drama, Western","1":"Action, Drama, Western","2":"Action, Drama, Western"},"Director":{"0":"Sergio Leone","1":"Sergio Leone","2":"Sergio Leone"},"Writer":{"0":"Adriano Bolzoni, Mark Lowell, V\u00edctor Andr\u00e9s Catena","1":"Adriano Bolzoni, Mark Lowell, V\u00edctor Andr\u00e9s Catena","2":"Adriano Bolzoni, Mark Lowell, V\u00edctor Andr\u00e9s Catena"},"Actors":{"0":"Clint Eastwood, Gian Maria Volont\u00e8, Marianne Koch","1":"Clint Eastwood, Gian Maria Volont\u00e8, Marianne Koch","2":"Clint Eastwood, Gian Maria Volont\u00e8, Marianne Koch"},"Plot":{"0":"A wandering gunfighter plays two rival families against each other in a town torn apart by greed, pride, and revenge.","1":"A wandering gunfighter plays two rival families against each other in a town torn apart by greed, pride, and revenge.","2":"A wandering gunfighter plays two rival families against each other in a town torn apart by greed, pride, and revenge."},"Language":{"0":"Italian, Spanish, Persian","1":"Italian, Spanish, Persian","2":"Italian, Spanish, Persian"},"Country":{"0":"Italy, Spain, West Germany","1":"Italy, Spain, West Germany","2":"Italy, Spain, West Germany"},"Awards":{"0":"1 win & 4 nominations","1":"1 win & 4 nominations","2":"1 win & 4 nominations"},"Poster":{"0":"https:\/\/m.media-amazon.com\/images\/M\/MV5BY2M5MDA1YjUtODQ1Yi00M2JlLTk2ZWQtYjI0NTEwZDk2NGNhXkEyXkFqcGdeQXVyMjUzOTY1NTc@._V1_SX300.jpg","1":"https:\/\/m.media-amazon.com\/images\/M\/MV5BY2M5MDA1YjUtODQ1Yi00M2JlLTk2ZWQtYjI0NTEwZDk2NGNhXkEyXkFqcGdeQXVyMjUzOTY1NTc@._V1_SX300.jpg","2":"https:\/\/m.media-amazon.com\/images\/M\/MV5BY2M5MDA1YjUtODQ1Yi00M2JlLTk2ZWQtYjI0NTEwZDk2NGNhXkEyXkFqcGdeQXVyMjUzOTY1NTc@._V1_SX300.jpg"},"Ratings":{"0":{"Source":"Internet Movie Database","Value":"7.9\/10"},"1":{"Source":"Rotten Tomatoes","Value":"96%"},"2":{"Source":"Metacritic","Value":"65\/100"}},"Metascore":{"0":"65","1":"65","2":"65"},"imdbRating":{"0":"7.9","1":"7.9","2":"7.9"},"imdbVotes":{"0":"220,812","1":"220,812","2":"220,812"},"imdbID":{"0":"tt0058461","1":"tt0058461","2":"tt0058461"},"Type":{"0":"movie","1":"movie","2":"movie"},"DVD":{"0":"01 Aug 2006","1":"01 Aug 2006","2":"01 Aug 2006"},"BoxOffice":{"0":"$14,500,000","1":"$14,500,000","2":"$14,500,000"},"Production":{"0":"N\/A","1":"N\/A","2":"N\/A"},"Website":{"0":"N\/A","1":"N\/A","2":"N\/A"},"Response":{"0":"True","1":"True","2":"True"}}