{"Title":{"0":"All About Eve","1":"All About Eve","2":"All About Eve"},"Year":{"0":"1950","1":"1950","2":"1950"},"Rated":{"0":"Passed","1":"Passed","2":"Passed"},"Released":{"0":"27 Oct 1950","1":"27 Oct 1950","2":"27 Oct 1950"},"Runtime":{"0":"138 min","1":"138 min","2":"138 min"},"Genre":{"0":"Drama","1":"Drama","2":"Drama"},"Director":{"0":"Joseph L. Mankiewicz","1":"Joseph L. Mankiewicz","2":"Joseph L. Mankiewicz"},"Writer":{"0":"Joseph L. Mankiewicz, Mary Orr","1":"Joseph L. Mankiewicz, Mary Orr","2":"Joseph L. Mankiewicz, Mary Orr"},"Actors":{"0":"Bette Davis, Anne Baxter, George Sanders","1":"Bette Davis, Anne Baxter, George Sanders","2":"Bette Davis, Anne Baxter, George Sanders"},"Plot":{"0":"A seemingly timid but secretly ruthless ing\u00e9nue insinuates herself into the lives of an aging Broadway star and her circle of theater friends.","1":"A seemingly timid but secretly ruthless ing\u00e9nue insinuates herself into the lives of an aging Broadway star and her circle of theater friends.","2":"A seemingly timid but secretly ruthless ing\u00e9nue insinuates herself into the lives of an aging Broadway star and her circle of theater friends."},"Language":{"0":"English, French","1":"English, French","2":"English, French"},"Country":{"0":"United States","1":"United States","2":"United States"},"Awards":{"0":"Won 6 Oscars. 27 wins & 20 nominations total","1":"Won 6 Oscars. 27 wins & 20 nominations total","2":"Won 6 Oscars. 27 wins & 20 nominations total"},"Poster":{"0":"https:\/\/m.media-amazon.com\/images\/M\/MV5BMTY2MTAzODI5NV5BMl5BanBnXkFtZTgwMjM4NzQ0MjE@._V1_SX300.jpg","1":"https:\/\/m.media-amazon.com\/images\/M\/MV5BMTY2MTAzODI5NV5BMl5BanBnXkFtZTgwMjM4NzQ0MjE@._V1_SX300.jpg","2":"https:\/\/m.media-amazon.com\/images\/M\/MV5BMTY2MTAzODI5NV5BMl5BanBnXkFtZTgwMjM4NzQ0MjE@._V1_SX300.jpg"},"Ratings":{"0":{"Source":"Internet Movie Database","Value":"8.2\/10"},"1":{"Source":"Rotten Tomatoes","Value":"99%"},"2":{"Source":"Metacritic","Value":"98\/100"}},"Metascore":{"0":"98","1":"98","2":"98"},"imdbRating":{"0":"8.2","1":"8.2","2":"8.2"},"imdbVotes":{"0":"132,804","1":"132,804","2":"132,804"},"imdbID":{"0":"tt0042192","1":"tt0042192","2":"tt0042192"},"Type":{"0":"movie","1":"movie","2":"movie"},"DVD":{"0":"05 Feb 2004","1":"05 Feb 2004","2":"05 Feb 2004"},"BoxOffice":{"0":"$63,463","1":"$63,463","2":"$63,463"},"Production":{"0":"N\/A","1":"N\/A","2":"N\/A"},"Website":{"0":"N\/A","1":"N\/A","2":"N\/A"},"Response":{"0":"True","1":"True","2":"True"}}