{"Title":{"0":"Giant","1":"Giant","2":"Giant"},"Year":{"0":"1956","1":"1956","2":"1956"},"Rated":{"0":"G","1":"G","2":"G"},"Released":{"0":"24 Nov 1956","1":"24 Nov 1956","2":"24 Nov 1956"},"Runtime":{"0":"201 min","1":"201 min","2":"201 min"},"Genre":{"0":"Drama, Western","1":"Drama, Western","2":"Drama, Western"},"Director":{"0":"George Stevens","1":"George Stevens","2":"George Stevens"},"Writer":{"0":"Edna Ferber, Fred Guiol, Ivan Moffat","1":"Edna Ferber, Fred Guiol, Ivan Moffat","2":"Edna Ferber, Fred Guiol, Ivan Moffat"},"Actors":{"0":"Elizabeth Taylor, Rock Hudson, James Dean","1":"Elizabeth Taylor, Rock Hudson, James Dean","2":"Elizabeth Taylor, Rock Hudson, James Dean"},"Plot":{"0":"Sprawling epic covering the life of a Texas cattle rancher and his family and associates.","1":"Sprawling epic covering the life of a Texas cattle rancher and his family and associates.","2":"Sprawling epic covering the life of a Texas cattle rancher and his family and associates."},"Language":{"0":"English, Spanish","1":"English, Spanish","2":"English, Spanish"},"Country":{"0":"United States","1":"United States","2":"United States"},"Awards":{"0":"Won 1 Oscar. 7 wins & 16 nominations total","1":"Won 1 Oscar. 7 wins & 16 nominations total","2":"Won 1 Oscar. 7 wins & 16 nominations total"},"Poster":{"0":"https:\/\/m.media-amazon.com\/images\/M\/MV5BMDQwOWQ0OGItNjJjYi00YzVjLTk4NmUtYzQ0NzUwZGY3NDZjXkEyXkFqcGdeQXVyMjUzOTY1NTc@._V1_SX300.jpg","1":"https:\/\/m.media-amazon.com\/images\/M\/MV5BMDQwOWQ0OGItNjJjYi00YzVjLTk4NmUtYzQ0NzUwZGY3NDZjXkEyXkFqcGdeQXVyMjUzOTY1NTc@._V1_SX300.jpg","2":"https:\/\/m.media-amazon.com\/images\/M\/MV5BMDQwOWQ0OGItNjJjYi00YzVjLTk4NmUtYzQ0NzUwZGY3NDZjXkEyXkFqcGdeQXVyMjUzOTY1NTc@._V1_SX300.jpg"},"Ratings":{"0":{"Source":"Internet Movie Database","Value":"7.6\/10"},"1":{"Source":"Rotten Tomatoes","Value":"88%"},"2":{"Source":"Metacritic","Value":"84\/100"}},"Metascore":{"0":"84","1":"84","2":"84"},"imdbRating":{"0":"7.6","1":"7.6","2":"7.6"},"imdbVotes":{"0":"39,992","1":"39,992","2":"39,992"},"imdbID":{"0":"tt0049261","1":"tt0049261","2":"tt0049261"},"Type":{"0":"movie","1":"movie","2":"movie"},"DVD":{"0":"20 Sep 2005","1":"20 Sep 2005","2":"20 Sep 2005"},"BoxOffice":{"0":"$32,855,818","1":"$32,855,818","2":"$32,855,818"},"Production":{"0":"N\/A","1":"N\/A","2":"N\/A"},"Website":{"0":"N\/A","1":"N\/A","2":"N\/A"},"Response":{"0":"True","1":"True","2":"True"}}