{"Title":{"0":"Her","1":"Her","2":"Her"},"Year":{"0":"2013","1":"2013","2":"2013"},"Rated":{"0":"R","1":"R","2":"R"},"Released":{"0":"10 Jan 2014","1":"10 Jan 2014","2":"10 Jan 2014"},"Runtime":{"0":"126 min","1":"126 min","2":"126 min"},"Genre":{"0":"Drama, Romance, Sci-Fi","1":"Drama, Romance, Sci-Fi","2":"Drama, Romance, Sci-Fi"},"Director":{"0":"Spike Jonze","1":"Spike Jonze","2":"Spike Jonze"},"Writer":{"0":"Spike Jonze","1":"Spike Jonze","2":"Spike Jonze"},"Actors":{"0":"Joaquin Phoenix, Amy Adams, Scarlett Johansson","1":"Joaquin Phoenix, Amy Adams, Scarlett Johansson","2":"Joaquin Phoenix, Amy Adams, Scarlett Johansson"},"Plot":{"0":"In a near future, a lonely writer develops an unlikely relationship with an operating system designed to meet his every need.","1":"In a near future, a lonely writer develops an unlikely relationship with an operating system designed to meet his every need.","2":"In a near future, a lonely writer develops an unlikely relationship with an operating system designed to meet his every need."},"Language":{"0":"English","1":"English","2":"English"},"Country":{"0":"United States","1":"United States","2":"United States"},"Awards":{"0":"Won 1 Oscar. 83 wins & 186 nominations total","1":"Won 1 Oscar. 83 wins & 186 nominations total","2":"Won 1 Oscar. 83 wins & 186 nominations total"},"Poster":{"0":"https:\/\/m.media-amazon.com\/images\/M\/MV5BMjA1Nzk0OTM2OF5BMl5BanBnXkFtZTgwNjU2NjEwMDE@._V1_SX300.jpg","1":"https:\/\/m.media-amazon.com\/images\/M\/MV5BMjA1Nzk0OTM2OF5BMl5BanBnXkFtZTgwNjU2NjEwMDE@._V1_SX300.jpg","2":"https:\/\/m.media-amazon.com\/images\/M\/MV5BMjA1Nzk0OTM2OF5BMl5BanBnXkFtZTgwNjU2NjEwMDE@._V1_SX300.jpg"},"Ratings":{"0":{"Source":"Internet Movie Database","Value":"8.0\/10"},"1":{"Source":"Rotten Tomatoes","Value":"94%"},"2":{"Source":"Metacritic","Value":"91\/100"}},"Metascore":{"0":"91","1":"91","2":"91"},"imdbRating":{"0":"8.0","1":"8.0","2":"8.0"},"imdbVotes":{"0":"625,512","1":"625,512","2":"625,512"},"imdbID":{"0":"tt1798709","1":"tt1798709","2":"tt1798709"},"Type":{"0":"movie","1":"movie","2":"movie"},"DVD":{"0":"13 May 2014","1":"13 May 2014","2":"13 May 2014"},"BoxOffice":{"0":"$25,568,251","1":"$25,568,251","2":"$25,568,251"},"Production":{"0":"N\/A","1":"N\/A","2":"N\/A"},"Website":{"0":"N\/A","1":"N\/A","2":"N\/A"},"Response":{"0":"True","1":"True","2":"True"}}