{"Title":{"0":"La haine","1":"La haine"},"Year":{"0":"1995","1":"1995"},"Rated":{"0":"Not Rated","1":"Not Rated"},"Released":{"0":"23 Feb 1996","1":"23 Feb 1996"},"Runtime":{"0":"98 min","1":"98 min"},"Genre":{"0":"Crime, Drama","1":"Crime, Drama"},"Director":{"0":"Mathieu Kassovitz","1":"Mathieu Kassovitz"},"Writer":{"0":"Mathieu Kassovitz","1":"Mathieu Kassovitz"},"Actors":{"0":"Vincent Cassel, Hubert Kound\u00e9, Sa\u00efd Taghmaoui","1":"Vincent Cassel, Hubert Kound\u00e9, Sa\u00efd Taghmaoui"},"Plot":{"0":"24 hours in the lives of three young men in the French suburbs the day after a violent riot.","1":"24 hours in the lives of three young men in the French suburbs the day after a violent riot."},"Language":{"0":"French","1":"French"},"Country":{"0":"France, United States","1":"France, United States"},"Awards":{"0":"8 wins & 15 nominations","1":"8 wins & 15 nominations"},"Poster":{"0":"https:\/\/m.media-amazon.com\/images\/M\/MV5BOTQxOGU0OWUtMzExYy00ZjIxLWJmMzAtNTI1Y2YxYTMxN2RkXkEyXkFqcGdeQXVyMjUzOTY1NTc@._V1_SX300.jpg","1":"https:\/\/m.media-amazon.com\/images\/M\/MV5BOTQxOGU0OWUtMzExYy00ZjIxLWJmMzAtNTI1Y2YxYTMxN2RkXkEyXkFqcGdeQXVyMjUzOTY1NTc@._V1_SX300.jpg"},"Ratings":{"0":{"Source":"Internet Movie Database","Value":"8.1\/10"},"1":{"Source":"Rotten Tomatoes","Value":"100%"}},"Metascore":{"0":"N\/A","1":"N\/A"},"imdbRating":{"0":"8.1","1":"8.1"},"imdbVotes":{"0":"177,980","1":"177,980"},"imdbID":{"0":"tt0113247","1":"tt0113247"},"Type":{"0":"movie","1":"movie"},"DVD":{"0":"17 Apr 2007","1":"17 Apr 2007"},"BoxOffice":{"0":"$280,859","1":"$280,859"},"Production":{"0":"N\/A","1":"N\/A"},"Website":{"0":"N\/A","1":"N\/A"},"Response":{"0":"True","1":"True"}}