{"Title":{"0":"M","1":"M"},"Year":{"0":"1931","1":"1931"},"Rated":{"0":"Passed","1":"Passed"},"Released":{"0":"31 Aug 1931","1":"31 Aug 1931"},"Runtime":{"0":"99 min","1":"99 min"},"Genre":{"0":"Crime, Mystery, Thriller","1":"Crime, Mystery, Thriller"},"Director":{"0":"Fritz Lang","1":"Fritz Lang"},"Writer":{"0":"Thea von Harbou, Fritz Lang, Egon Jacobsohn","1":"Thea von Harbou, Fritz Lang, Egon Jacobsohn"},"Actors":{"0":"Peter Lorre, Ellen Widmann, Inge Landgut","1":"Peter Lorre, Ellen Widmann, Inge Landgut"},"Plot":{"0":"When the police in a German city are unable to catch a child-murderer, other criminals join in the manhunt.","1":"When the police in a German city are unable to catch a child-murderer, other criminals join in the manhunt."},"Language":{"0":"German","1":"German"},"Country":{"0":"Germany","1":"Germany"},"Awards":{"0":"2 wins","1":"2 wins"},"Poster":{"0":"https:\/\/m.media-amazon.com\/images\/M\/MV5BODA4ODk3OTEzMF5BMl5BanBnXkFtZTgwMTQ2ODMwMzE@._V1_SX300.jpg","1":"https:\/\/m.media-amazon.com\/images\/M\/MV5BODA4ODk3OTEzMF5BMl5BanBnXkFtZTgwMTQ2ODMwMzE@._V1_SX300.jpg"},"Ratings":{"0":{"Source":"Internet Movie Database","Value":"8.3\/10"},"1":{"Source":"Rotten Tomatoes","Value":"100%"}},"Metascore":{"0":"N\/A","1":"N\/A"},"imdbRating":{"0":"8.3","1":"8.3"},"imdbVotes":{"0":"160,186","1":"160,186"},"imdbID":{"0":"tt0022100","1":"tt0022100"},"Type":{"0":"movie","1":"movie"},"DVD":{"0":"14 Dec 2004","1":"14 Dec 2004"},"BoxOffice":{"0":"$35,566","1":"$35,566"},"Production":{"0":"Paramount Pictures","1":"Paramount Pictures"},"Website":{"0":"N\/A","1":"N\/A"},"Response":{"0":"True","1":"True"}}