{"Title":{"0":"My Father and My Son"},"Year":{"0":"2005"},"Rated":{"0":"Not Rated"},"Released":{"0":"18 Nov 2005"},"Runtime":{"0":"112 min"},"Genre":{"0":"Drama, Family"},"Director":{"0":"\u00c7agan Irmak"},"Writer":{"0":"\u00c7agan Irmak"},"Actors":{"0":"\u00c7etin Tekindor, Fikret Kuskan, H\u00fcmeyra"},"Plot":{"0":"The family of a left-wing journalist is torn apart after the military coup of Turkey in 1980."},"Language":{"0":"Turkish"},"Country":{"0":"Turkey"},"Awards":{"0":"14 wins & 7 nominations"},"Poster":{"0":"https:\/\/m.media-amazon.com\/images\/M\/MV5BNjAzMzEwYzctNjc1MC00Nzg5LWFmMGItMTgzYmMyNTY2OTQ4XkEyXkFqcGdeQXVyNjU0OTQ0OTY@._V1_SX300.jpg"},"Ratings":{"0":{"Source":"Internet Movie Database","Value":"8.2\/10"}},"Metascore":{"0":"N\/A"},"imdbRating":{"0":"8.2"},"imdbVotes":{"0":"87,422"},"imdbID":{"0":"tt0476735"},"Type":{"0":"movie"},"DVD":{"0":"01 May 2018"},"BoxOffice":{"0":"N\/A"},"Production":{"0":"N\/A"},"Website":{"0":"N\/A"},"Response":{"0":"True"}}