{"Title":{"0":"PK","1":"PK"},"Year":{"0":"2014","1":"2014"},"Rated":{"0":"Not Rated","1":"Not Rated"},"Released":{"0":"19 Dec 2014","1":"19 Dec 2014"},"Runtime":{"0":"153 min","1":"153 min"},"Genre":{"0":"Comedy, Drama, Sci-Fi","1":"Comedy, Drama, Sci-Fi"},"Director":{"0":"Rajkumar Hirani","1":"Rajkumar Hirani"},"Writer":{"0":"Rajkumar Hirani, Abhijat Joshi","1":"Rajkumar Hirani, Abhijat Joshi"},"Actors":{"0":"Aamir Khan, Anushka Sharma, Sanjay Dutt","1":"Aamir Khan, Anushka Sharma, Sanjay Dutt"},"Plot":{"0":"An alien on Earth loses the only device he can use to communicate with his spaceship. His innocent nature and child-like questions force the country to evaluate the impact of there religious views on there people.","1":"An alien on Earth loses the only device he can use to communicate with his spaceship. His innocent nature and child-like questions force the country to evaluate the impact of there religious views on there people."},"Language":{"0":"Hindi","1":"Hindi"},"Country":{"0":"India","1":"India"},"Awards":{"0":"20 wins & 23 nominations","1":"20 wins & 23 nominations"},"Poster":{"0":"https:\/\/m.media-amazon.com\/images\/M\/MV5BMTYzOTE2NjkxN15BMl5BanBnXkFtZTgwMDgzMTg0MzE@._V1_SX300.jpg","1":"https:\/\/m.media-amazon.com\/images\/M\/MV5BMTYzOTE2NjkxN15BMl5BanBnXkFtZTgwMDgzMTg0MzE@._V1_SX300.jpg"},"Ratings":{"0":{"Source":"Internet Movie Database","Value":"8.1\/10"},"1":{"Source":"Rotten Tomatoes","Value":"78%"}},"Metascore":{"0":"N\/A","1":"N\/A"},"imdbRating":{"0":"8.1","1":"8.1"},"imdbVotes":{"0":"190,979","1":"190,979"},"imdbID":{"0":"tt2338151","1":"tt2338151"},"Type":{"0":"movie","1":"movie"},"DVD":{"0":"26 Mar 2017","1":"26 Mar 2017"},"BoxOffice":{"0":"$10,616,104","1":"$10,616,104"},"Production":{"0":"UTV Motion Pictures","1":"UTV Motion Pictures"},"Website":{"0":"N\/A","1":"N\/A"},"Response":{"0":"True","1":"True"}}