{"Title":{"0":"The Secret in Their Eyes","1":"The Secret in Their Eyes","2":"The Secret in Their Eyes"},"Year":{"0":"2009","1":"2009","2":"2009"},"Rated":{"0":"R","1":"R","2":"R"},"Released":{"0":"21 May 2010","1":"21 May 2010","2":"21 May 2010"},"Runtime":{"0":"129 min","1":"129 min","2":"129 min"},"Genre":{"0":"Drama, Mystery, Romance","1":"Drama, Mystery, Romance","2":"Drama, Mystery, Romance"},"Director":{"0":"Juan Jos\u00e9 Campanella","1":"Juan Jos\u00e9 Campanella","2":"Juan Jos\u00e9 Campanella"},"Writer":{"0":"Eduardo Sacheri, Juan Jos\u00e9 Campanella","1":"Eduardo Sacheri, Juan Jos\u00e9 Campanella","2":"Eduardo Sacheri, Juan Jos\u00e9 Campanella"},"Actors":{"0":"Ricardo Dar\u00edn, Soledad Villamil, Pablo Rago","1":"Ricardo Dar\u00edn, Soledad Villamil, Pablo Rago","2":"Ricardo Dar\u00edn, Soledad Villamil, Pablo Rago"},"Plot":{"0":"A retired legal counselor writes a novel hoping to find closure for one of his past unresolved homicide cases and for his unreciprocated love with his superior - both of which still haunt him decades later.","1":"A retired legal counselor writes a novel hoping to find closure for one of his past unresolved homicide cases and for his unreciprocated love with his superior - both of which still haunt him decades later.","2":"A retired legal counselor writes a novel hoping to find closure for one of his past unresolved homicide cases and for his unreciprocated love with his superior - both of which still haunt him decades later."},"Language":{"0":"Spanish","1":"Spanish","2":"Spanish"},"Country":{"0":"Argentina, Spain","1":"Argentina, Spain","2":"Argentina, Spain"},"Awards":{"0":"Won 1 Oscar. 53 wins & 43 nominations total","1":"Won 1 Oscar. 53 wins & 43 nominations total","2":"Won 1 Oscar. 53 wins & 43 nominations total"},"Poster":{"0":"https:\/\/m.media-amazon.com\/images\/M\/MV5BY2FhZGI5M2QtZWFiZS00NjkwLWE4NWQtMzg3ZDZjNjdkYTJiXkEyXkFqcGdeQXVyMTMxODk2OTU@._V1_SX300.jpg","1":"https:\/\/m.media-amazon.com\/images\/M\/MV5BY2FhZGI5M2QtZWFiZS00NjkwLWE4NWQtMzg3ZDZjNjdkYTJiXkEyXkFqcGdeQXVyMTMxODk2OTU@._V1_SX300.jpg","2":"https:\/\/m.media-amazon.com\/images\/M\/MV5BY2FhZGI5M2QtZWFiZS00NjkwLWE4NWQtMzg3ZDZjNjdkYTJiXkEyXkFqcGdeQXVyMTMxODk2OTU@._V1_SX300.jpg"},"Ratings":{"0":{"Source":"Internet Movie Database","Value":"8.2\/10"},"1":{"Source":"Rotten Tomatoes","Value":"89%"},"2":{"Source":"Metacritic","Value":"80\/100"}},"Metascore":{"0":"80","1":"80","2":"80"},"imdbRating":{"0":"8.2","1":"8.2","2":"8.2"},"imdbVotes":{"0":"212,240","1":"212,240","2":"212,240"},"imdbID":{"0":"tt1305806","1":"tt1305806","2":"tt1305806"},"Type":{"0":"movie","1":"movie","2":"movie"},"DVD":{"0":"21 Sep 2010","1":"21 Sep 2010","2":"21 Sep 2010"},"BoxOffice":{"0":"$6,391,436","1":"$6,391,436","2":"$6,391,436"},"Production":{"0":"Sony Pictures Classics","1":"Sony Pictures Classics","2":"Sony Pictures Classics"},"Website":{"0":"N\/A","1":"N\/A","2":"N\/A"},"Response":{"0":"True","1":"True","2":"True"}}