{"Title":{"0":"Unforgiven","1":"Unforgiven","2":"Unforgiven"},"Year":{"0":"1992","1":"1992","2":"1992"},"Rated":{"0":"R","1":"R","2":"R"},"Released":{"0":"07 Aug 1992","1":"07 Aug 1992","2":"07 Aug 1992"},"Runtime":{"0":"130 min","1":"130 min","2":"130 min"},"Genre":{"0":"Drama, Western","1":"Drama, Western","2":"Drama, Western"},"Director":{"0":"Clint Eastwood","1":"Clint Eastwood","2":"Clint Eastwood"},"Writer":{"0":"David Webb Peoples","1":"David Webb Peoples","2":"David Webb Peoples"},"Actors":{"0":"Clint Eastwood, Gene Hackman, Morgan Freeman","1":"Clint Eastwood, Gene Hackman, Morgan Freeman","2":"Clint Eastwood, Gene Hackman, Morgan Freeman"},"Plot":{"0":"Retired Old West gunslinger William Munny reluctantly takes on one last job, with the help of his old partner Ned Logan and a young man, The \"Schofield Kid.\"","1":"Retired Old West gunslinger William Munny reluctantly takes on one last job, with the help of his old partner Ned Logan and a young man, The \"Schofield Kid.\"","2":"Retired Old West gunslinger William Munny reluctantly takes on one last job, with the help of his old partner Ned Logan and a young man, The \"Schofield Kid.\""},"Language":{"0":"English","1":"English","2":"English"},"Country":{"0":"United States","1":"United States","2":"United States"},"Awards":{"0":"Won 4 Oscars. 50 wins & 47 nominations total","1":"Won 4 Oscars. 50 wins & 47 nominations total","2":"Won 4 Oscars. 50 wins & 47 nominations total"},"Poster":{"0":"https:\/\/m.media-amazon.com\/images\/M\/MV5BODM3YWY4NmQtN2Y3Ni00OTg0LWFhZGQtZWE3ZWY4MTJlOWU4XkEyXkFqcGdeQXVyNjU0OTQ0OTY@._V1_SX300.jpg","1":"https:\/\/m.media-amazon.com\/images\/M\/MV5BODM3YWY4NmQtN2Y3Ni00OTg0LWFhZGQtZWE3ZWY4MTJlOWU4XkEyXkFqcGdeQXVyNjU0OTQ0OTY@._V1_SX300.jpg","2":"https:\/\/m.media-amazon.com\/images\/M\/MV5BODM3YWY4NmQtN2Y3Ni00OTg0LWFhZGQtZWE3ZWY4MTJlOWU4XkEyXkFqcGdeQXVyNjU0OTQ0OTY@._V1_SX300.jpg"},"Ratings":{"0":{"Source":"Internet Movie Database","Value":"8.2\/10"},"1":{"Source":"Rotten Tomatoes","Value":"96%"},"2":{"Source":"Metacritic","Value":"85\/100"}},"Metascore":{"0":"85","1":"85","2":"85"},"imdbRating":{"0":"8.2","1":"8.2","2":"8.2"},"imdbVotes":{"0":"415,957","1":"415,957","2":"415,957"},"imdbID":{"0":"tt0105695","1":"tt0105695","2":"tt0105695"},"Type":{"0":"movie","1":"movie","2":"movie"},"DVD":{"0":"30 Oct 2001","1":"30 Oct 2001","2":"30 Oct 2001"},"BoxOffice":{"0":"$101,167,799","1":"$101,167,799","2":"$101,167,799"},"Production":{"0":"N\/A","1":"N\/A","2":"N\/A"},"Website":{"0":"N\/A","1":"N\/A","2":"N\/A"},"Response":{"0":"True","1":"True","2":"True"}}